src/__init__.py
src/auth.py
pi_lab_jupyter_pi_service-0.0.1.dist-info/METADATA
pi_lab_jupyter_pi_service-0.0.1.dist-info/WHEEL
pi_lab_jupyter_pi_service-0.0.1.dist-info/top_level.txt
pi_lab_jupyter_pi_service-0.0.1.dist-info/RECORD
